MANIFEST.in
setup.py
restutils/__init__.py
restutils/_restclient.py
restutils.egg-info/PKG-INFO
restutils.egg-info/SOURCES.txt
restutils.egg-info/dependency_links.txt
restutils.egg-info/top_level.txt