Metadata-Version: 1.1
Name: restutils
Version: 1.0.3
Summary: Provides libraries for REST API applications
Home-page: https://github.com/pupattan/restutils
Author: pulak pattanayak
Author-email: pulak.pattanayak@gmail.com
License: MIT
Keywords: rest http
Platform: UNKNOWN
Classifier: License :: OSI Approved :: MIT License
Classifier: Programming Language :: Python :: 2
Classifier: Programming Language :: Python :: 3
